{"dct_title_s": "School Districts Colorado 1991","dct_description_sm": ["This polygon data layer represents school districts for Colorado in 1991. The dataset was originally published by the Colorado Department of Local Affairs-Division of Local Government in 2005.[The export file schoolbd.e00 imports into a coverage with statewide school district boundaries. These boundaries were developed in 1991 under contract with the Colorado Department of Education for inclusion in the National Center for Education Statistics, U.S. Department of Education's Census Mapping Project. The boundaries were constructed from legal descriptions of each school district. These boundaries received rigorous quality control.]"],"dct_language_sm": ["eng"],"dct_creator_sm": ["Colorado Department of Local Affairs-Division of Local Government"],"schema_provider_s": "American Geographical Society Library – UWM Libraries","gbl_resourceClass_sm": ["Datasets"],"gbl_resourceType_sm": ["Polygon data"],"dcat_theme_sm": ["Boundaries"],"dct_temporal_sm": ["1991"],"dct_issued_s": "2005","gbl_indexYear_im": [1991],"dct_spatial_sm": ["Colorado"],"locn_geometry": "ENVELOPE(-101.868837, -109.279563, 41.071925, 36.923976)","dcat_bbox": "ENVELOPE(-109.279563, -101.868837, 41.071925, 36.923976)","dct_rights_sm": ["<a href=\"https://uwm.edu/libraries/digital-collections/copyright-digcoll/\">Please see the UWM Libraries statement on Copyright and Digital Collections</a>.","Although this data is being distributed by the American Geographical Society Library at the University of Wisconsin-Milwaukee Libraries, no warranty expressed or implied is made by the University as to the accuracy of the data and related materials. The act of distribution shall not constitute any such warranty, and no responsibility is assumed by the University in the use of this data, or related materials."],"dct_accessRights_s": "Public","dct_format_s": "Shapefile","dct_references_s": "{\"http://schema.org/url\":\"https://geodiscovery.uwm.edu/ark:-77981-gmgs5x25c15\",\"http://schema.org/downloadUrl\":\"https://geodata.uwm.edu/public/gmgs5x25c15/Colorado_SchoolDistricts_1991.zip\",\"http://www.isotc211.org/schemas/2005/gmd\":\"https://geodata.uwm.edu/metadata/gmgs5x25c15_ISO.xml\"}","id": "ark:-77981-gmgs5x25c15","dct_identifier_sm": ["ark:/77981/gmgs5x25c15"],"gbl_mdModified_dt": "2023-09-26T18:06:47.0790494Z","gbl_mdVersion_s": "Aardvark","gbl_suppressed_b": false}